MANIFEST.in
README.md
pyproject.toml
setup.py
proalgotrader_binary/__init__.py
proalgotrader_binary/main.cpython-311-x86_64-linux-gnu.so
proalgotrader_binary/run.cpython-311-x86_64-linux-gnu.so
proalgotrader_binary.egg-info/PKG-INFO
proalgotrader_binary.egg-info/SOURCES.txt
proalgotrader_binary.egg-info/dependency_links.txt
proalgotrader_binary.egg-info/requires.txt
proalgotrader_binary.egg-info/top_level.txt
proalgotrader_binary/hello/__init__.py
proalgotrader_binary/hello/test.cpython-311-x86_64-linux-gnu.so