Metadata-Version: 2.1
Name: proalgotrader-binary
Version: 0.0.2
Summary: ProAlgoTrader core
Home-page: https://github.com/krunaldodiya/proalgotrader_core
Author: Krunal Dodiya
Author-email: kunal.dodiya1@gmail.com
License: UNKNOWN
Platform: UNKNOWN
Classifier: Programming Language :: Python :: 3
Classifier: Operating System :: OS Independent
